LICENSE
aliexpress/__init__.py
aliexpress/api/__init__.py
aliexpress/api/base.py
aliexpress/api/rest/AppipGetRequest.py
aliexpress/api/rest/AppraiseRedefiningQuerysellerevaluationorderlistRequest.py
aliexpress/api/rest/AppraiseRedefiningSavesellerfeedbackRequest.py
aliexpress/api/rest/CainiaoGlobalHandoverCancelRequest.py
aliexpress/api/rest/CainiaoGlobalHandoverCloudprintGetRequest.py
aliexpress/api/rest/CainiaoGlobalHandoverCommitRequest.py
aliexpress/api/rest/CainiaoGlobalHandoverContentQueryRequest.py
aliexpress/api/rest/CainiaoGlobalHandoverParcelQueryRequest.py
aliexpress/api/rest/CainiaoGlobalHandoverPdfGetRequest.py
aliexpress/api/rest/CainiaoGlobalHandoverSavedraftRequest.py
aliexpress/api/rest/CainiaoGlobalHandoverUpdateRequest.py
aliexpress/api/rest/CainiaoGlobalLogisticOrderCreateRequest.py
aliexpress/api/rest/CainiaoGlobalSolutionInquiryRequest.py
aliexpress/api/rest/CainiaoGlobalSolutionServiceResourceQueryRequest.py
aliexpress/api/rest/CategoryRedefiningGetallchildattributesresultRequest.py
aliexpress/api/rest/CategoryRedefiningGetchildattributesresultbypostcateidandpathRequest.py
aliexpress/api/rest/CategoryRedefiningGetchildrenpostcategorybyidRequest.py
aliexpress/api/rest/CategoryRedefiningGetpostcategorybyidRequest.py
aliexpress/api/rest/CategoryRedefiningSizemodelsrequiredforpostcatRequest.py
aliexpress/api/rest/DataRedefiningQueryproductaddcartinfoeverydaybyidRequest.py
aliexpress/api/rest/DataRedefiningQueryproductbusinessinfobyidRequest.py
aliexpress/api/rest/DataRedefiningQueryproductexposedinfoeverydaybyidRequest.py
aliexpress/api/rest/DataRedefiningQueryproductfavoritedinfoeverydaybyidRequest.py
aliexpress/api/rest/DataRedefiningQueryproductsalesinfoeverydaybyidRequest.py
aliexpress/api/rest/DataRedefiningQueryproductviewedinfoeverydaybyidRequest.py
aliexpress/api/rest/DistributorOrderQueryRequest.py
aliexpress/api/rest/EvaluationEvaluationReplyRequest.py
aliexpress/api/rest/EvaluationListorderevaluationGetRequest.py
aliexpress_sdk-0.1.2.dist-info/entry_points.txt
aliexpress_sdk-0.1.2.dist-info/LICENSE
aliexpress_sdk-0.1.2.dist-info/WHEEL
aliexpress_sdk-0.1.2.dist-info/METADATA
aliexpress_sdk-0.1.2.dist-info/RECORD
