Metadata-Version: 2.1
Name: aliexpress-sdk
Version: 0.1.2
Summary: Python wrapper of the AliExpress API for sellers
Home-page: https://github.com/bayborodin/aliexpress-sdk
License: MIT
Keywords: aliexpress,api,sdk
Author: Nicholas Bayborodin
Author-email: nicholas.bayborodin@gmail.com
Requires-Python: >=3.6,<4.0
Classifier: Development Status :: 3 - Alpha
Classifier: Intended Audience :: Developers
Classifier: License :: OSI Approved :: MIT License
Classifier: Operating System :: OS Independent
Classifier: Programming Language :: Python :: 3
Classifier: Programming Language :: Python :: 3.6
Classifier: Programming Language :: Python :: 3.7
Classifier: Programming Language :: Python :: 3.8
Classifier: Programming Language :: Python :: 3.9
Classifier: Topic :: Software Development :: Libraries :: Python Modules
Requires-Dist: flake8 (>=3.8.4,<4.0.0)
Project-URL: Repository, https://github.com/bayborodin/aliexpress-sdk
